argo_client/__init__.py
argo_client/connection.py
argo_client/interaction.py
argo_client/netstring.py
argo_client/py.typed
argo_client-0.0.14.dist-info/METADATA
argo_client-0.0.14.dist-info/WHEEL
argo_client-0.0.14.dist-info/licenses/LICENSE
argo_client-0.0.14.dist-info/RECORD
